pydra/tasks/ants/__init__.py
pydra/tasks/ants/apply_transforms.py
pydra/tasks/ants/bias_correction.py
pydra/tasks/ants/create_jacobian_determinant_image.py
pydra/tasks/ants/registration.py
clinica_pydra_ants-0.1.1.dist-info/METADATA
clinica_pydra_ants-0.1.1.dist-info/WHEEL
clinica_pydra_ants-0.1.1.dist-info/licenses/LICENSE
clinica_pydra_ants-0.1.1.dist-info/RECORD
